LICENSE.md
MANIFEST.in
README.md
requirements.txt
setup.cfg
setup.py
starsaiot_monit/__init__.py
starsaiot_monit/conf.py
starsaiot_monit/logger.py
starsaiot_monit/smonit.py
starsaiot_monit.egg-info/PKG-INFO
starsaiot_monit.egg-info/SOURCES.txt
starsaiot_monit.egg-info/dependency_links.txt
starsaiot_monit.egg-info/entry_points.txt
starsaiot_monit.egg-info/requires.txt
starsaiot_monit.egg-info/top_level.txt
starsaiot_monit/config/__init__.py
starsaiot_monit/monit/__init__.py
starsaiot_monit/monit/monit_service.py
starsaiot_monit/monit/mqtt_connector.py
starsaiot_monit/monit/test.py
starsaiot_monit/monit/utils/__init__.py
starsaiot_monit/monit/utils/device_utils.py
starsaiot_monit/monit/utils/local_storage.py
starsaiot_monit/monit/utils/local_storage_old.py
starsaiot_monit/monit/utils/md5.py
starsaiot_monit/monit/utils/sftp.py
starsaiot_monit/monit/utils/simInfo.py