Metadata-Version: 2.1
Name: starsaiot-monit
Version: 1.2.25
Summary: 监控平台
Home-page: https://github.com/huamoai/starsaiot_monit
Author: wangning
Author-email: 879619544@qq.com
License: BSD
Download-URL: https://github.com/huamoai/starsaiot_monit/tarball/1.2.25
Platform: UNKNOWN
Classifier: Development Status :: 3 - Alpha
Classifier: Intended Audience :: Developers
Classifier: Programming Language :: Python :: 3
Requires-Python: >=3.6
License-File: LICENSE.md
